exsc/ExtendedSubCipher.py
exsc/__init__.py
exsc-1.2.dist-info/LICENSE
exsc-1.2.dist-info/METADATA
exsc-1.2.dist-info/WHEEL
exsc-1.2.dist-info/top_level.txt
exsc-1.2.dist-info/RECORD
